{"namespace":"Big3AstrologyDesignSystem_becd02","components":[{"name":"Logo","sourcePath":"components/brand/Logo.jsx"},{"name":"CelestialDivider","sourcePath":"components/celestial/CelestialDivider.jsx"},{"name":"StarRating","sourcePath":"components/celestial/StarRating.jsx"},{"name":"TrinityMark","sourcePath":"components/celestial/TrinityMark.jsx"},{"name":"ZodiacGlyph","sourcePath":"components/celestial/ZodiacGlyph.jsx"},{"name":"Badge","sourcePath":"components/core/Badge.jsx"},{"name":"Button","sourcePath":"components/core/Button.jsx"},{"name":"Card","sourcePath":"components/core/Card.jsx"},{"name":"Eyebrow","sourcePath":"components/core/Eyebrow.jsx"}],"startingPoints":[{"name":"TrinityMark","path":"components/celestial/TrinityMark.jsx","previewPath":"components/celestial/celestial.card.html","kind":"component","section":"Celestial","subtitle":"Big 3 triangle icon mark","viewport":"700x160"},{"name":"Badge","path":"components/core/Badge.jsx","previewPath":"components/core/core.card.html","kind":"component","section":"Core","subtitle":"Category & status chip","viewport":"700x140"},{"name":"Button","path":"components/core/Button.jsx","previewPath":"components/core/core.card.html","kind":"component","section":"Core","subtitle":"Branded action button","viewport":"700x150"},{"name":"Card","path":"components/core/Card.jsx","previewPath":"components/core/core.card.html","kind":"component","section":"Core","subtitle":"Surface card container","viewport":"700x220"},{"name":"instagram","path":"ui_kits/instagram/index.html","previewPath":"ui_kits/instagram/index.html","kind":"screen","section":"Instagram","subtitle":"Big 3 feed — profile grid, scrolling feed & 7 post templates","viewport":"1024x920"},{"name":"website","path":"ui_kits/website/index.html","previewPath":"ui_kits/website/index.html","kind":"screen","section":"Website","subtitle":"Astrology consulting landing + booking flow","viewport":"1180x900"}],"cards":[{"path":"guidelines/brand-logos.card.html","group":"Brand","viewport":"700x200","subtitle":"Full color, reversed & monochrome","name":"Logo Lockups"},{"path":"guidelines/brand-motifs.card.html","group":"Brand","viewport":"700x220","subtitle":"Connectors, dividers & line-work that recur across the feed","name":"Celestial Motifs"},{"path":"guidelines/brand-trinity.card.html","group":"Brand","viewport":"700x190","subtitle":"The three luminaries of the Big 3","name":"Trinity Glyphs"},{"path":"guidelines/color-brand-triad.card.html","group":"Colors","viewport":"700x215","subtitle":"Sun · Moon · Ascendant — the three pillars","name":"Brand Triad"},{"path":"guidelines/color-surfaces.card.html","group":"Colors","viewport":"700x160","subtitle":"Warm cream grounds and color blocks","name":"Surfaces & Paper"},{"path":"guidelines/color-tints.card.html","group":"Colors","viewport":"700x150","subtitle":"Working values across the triad","name":"Brand Tints & Shades"},{"path":"components/brand/logo.card.html","group":"Components","viewport":"700x300","subtitle":"Full wordmark lockups across backgrounds","name":"Logo"},{"path":"components/celestial/celestial.card.html","group":"Components","viewport":"700x320","subtitle":"The brand's astrological vocabulary","name":"Celestial — Mark · Glyphs · Divider · Rating"},{"path":"components/core/core.card.html","group":"Components","viewport":"700x420","subtitle":"Brand primitives","name":"Core — Button · Badge · Eyebrow · Card"},{"path":"ui_kits/instagram/index.html","group":"Instagram","viewport":"700x760"},{"path":"guidelines/spacing-radii-shadows.card.html","group":"Spacing","viewport":"700x170","subtitle":"Restrained corners · soft wine-tinted elevation","name":"Radii & Shadows"},{"path":"guidelines/spacing-scale.card.html","group":"Spacing","viewport":"700x150","subtitle":"4px base · airy editorial rhythm","name":"Spacing Scale"},{"path":"guidelines/type-body.card.html","group":"Type","viewport":"700x210","subtitle":"Paragraphs, captions & interface text","name":"Body Sans — Mulish"},{"path":"guidelines/type-sans.card.html","group":"Type","viewport":"700x250","subtitle":"Wordmark, eyebrows & tracked ALL-CAPS labels","name":"Geometric Sans — Jost"},{"path":"guidelines/type-scale.card.html","group":"Type","viewport":"700x300","subtitle":"Display → caption, with role mapping","name":"Type Scale"},{"path":"guidelines/type-serif.card.html","group":"Type","viewport":"700x230","subtitle":"Editorial quotes & emotive hero lines","name":"Serif Display — Playfair"},{"path":"ui_kits/website/index.html","group":"Website","viewport":"1180x820"}],"globalCssPaths":["tokens/fonts.css","tokens/colors.css","tokens/typography.css","tokens/spacing.css","tokens/base.css","styles.css"],"tokens":[{"name":"--b3a-wine","value":"#A4426C","kind":"color","definedIn":"tokens/colors.css"},{"name":"--b3a-wine-deep","value":"#7C2F50","kind":"color","definedIn":"tokens/colors.css"},{"name":"--b3a-wine-700","value":"#8E3760","kind":"color","definedIn":"tokens/colors.css"},{"name":"--b3a-coral","value":"#F27678","kind":"color","definedIn":"tokens/colors.css"},{"name":"--b3a-coral-600","value":"#E85F61","kind":"color","definedIn":"tokens/colors.css"},{"name":"--b3a-coral-soft","value":"#F8A6A6","kind":"color","definedIn":"tokens/colors.css"},{"name":"--b3a-gold","value":"#E6A44E","kind":"color","definedIn":"tokens/colors.css"},{"name":"--b3a-gold-deep","value":"#C9852F","kind":"color","definedIn":"tokens/colors.css"},{"name":"--b3a-amber","value":"#E5A34D","kind":"color","definedIn":"tokens/colors.css"},{"name":"--b3a-ink","value":"#1B1B1B","kind":"color","definedIn":"tokens/colors.css"},{"name":"--b3a-ink-800","value":"#2A2A2A","kind":"color","definedIn":"tokens/colors.css"},{"name":"--b3a-charcoal","value":"#3D4047","kind":"color","definedIn":"tokens/colors.css"},{"name":"--b3a-ink-500","value":"#6E665F","kind":"color","definedIn":"tokens/colors.css"},{"name":"--b3a-ink-400","value":"#948B82","kind":"color","definedIn":"tokens/colors.css"},{"name":"--b3a-line","value":"#ECE0D5","kind":"color","definedIn":"tokens/colors.css"},{"name":"--b3a-line-strong","value":"#DBCBBC","kind":"color","definedIn":"tokens/colors.css"},{"name":"--b3a-cream","value":"#FEF9F5","kind":"color","definedIn":"tokens/colors.css"},{"name":"--b3a-ivory","value":"#FBF3EC","kind":"color","definedIn":"tokens/colors.css"},{"name":"--b3a-sand","value":"#F3E7DC","kind":"color","definedIn":"tokens/colors.css"},{"name":"--b3a-blush","value":"#F9E6E2","kind":"color","definedIn":"tokens/colors.css"},{"name":"--b3a-plum-wash","value":"#EFD9E1","kind":"color","definedIn":"tokens/colors.css"},{"name":"--b3a-white","value":"#FFFFFF","kind":"color","definedIn":"tokens/colors.css"},{"name":"--surface-page","value":"var(--b3a-cream)","kind":"color","definedIn":"tokens/colors.css"},{"name":"--surface-paper","value":"var(--b3a-ivory)","kind":"color","definedIn":"tokens/colors.css"},{"name":"--surface-card","value":"var(--b3a-white)","kind":"color","definedIn":"tokens/colors.css"},{"name":"--surface-sand","value":"var(--b3a-sand)","kind":"color","definedIn":"tokens/colors.css"},{"name":"--surface-blush","value":"var(--b3a-blush)","kind":"color","definedIn":"tokens/colors.css"},{"name":"--surface-inverse","value":"var(--b3a-charcoal)","kind":"color","definedIn":"tokens/colors.css"},{"name":"--surface-wine","value":"var(--b3a-wine)","kind":"color","definedIn":"tokens/colors.css"},{"name":"--surface-amber","value":"var(--b3a-amber)","kind":"color","definedIn":"tokens/colors.css"},{"name":"--text-primary","value":"var(--b3a-ink)","kind":"font","definedIn":"tokens/colors.css"},{"name":"--text-secondary","value":"var(--b3a-ink-500)","kind":"font","definedIn":"tokens/colors.css"},{"name":"--text-muted","value":"var(--b3a-ink-400)","kind":"font","definedIn":"tokens/colors.css"},{"name":"--text-on-color","value":"var(--b3a-cream)","kind":"font","definedIn":"tokens/colors.css"},{"name":"--text-on-wine","value":"#FBEAF0","kind":"font","definedIn":"tokens/colors.css"},{"name":"--brand-primary","value":"var(--b3a-wine)","kind":"color","definedIn":"tokens/colors.css"},{"name":"--brand-accent","value":"var(--b3a-coral)","kind":"color","definedIn":"tokens/colors.css"},{"name":"--brand-gold","value":"var(--b3a-gold)","kind":"color","definedIn":"tokens/colors.css"},{"name":"--border-subtle","value":"var(--b3a-line)","kind":"color","definedIn":"tokens/colors.css"},{"name":"--border-strong","value":"var(--b3a-line-strong)","kind":"color","definedIn":"tokens/colors.css"},{"name":"--border-ink","value":"var(--b3a-ink)","kind":"color","definedIn":"tokens/colors.css"},{"name":"--star","value":"var(--b3a-gold)","kind":"color","definedIn":"tokens/colors.css"},{"name":"--focus-ring","value":"var(--b3a-wine)","kind":"color","definedIn":"tokens/colors.css"},{"name":"--sun-color","value":"var(--b3a-coral)","kind":"color","definedIn":"tokens/colors.css"},{"name":"--moon-color","value":"var(--b3a-wine)","kind":"color","definedIn":"tokens/colors.css"},{"name":"--asc-color","value":"var(--b3a-gold)","kind":"color","definedIn":"tokens/colors.css"},{"name":"--font-serif","value":"'Playfair Display', 'Georgia', serif","kind":"font","definedIn":"tokens/typography.css"},{"name":"--font-sans","value":"'Jost', 'Century Gothic', 'Futura', system-ui, sans-serif","kind":"font","definedIn":"tokens/typography.css"},{"name":"--font-body","value":"'Mulish', system-ui, -apple-system, sans-serif","kind":"font","definedIn":"tokens/typography.css"},{"name":"--font-display","value":"var(--font-serif)","kind":"font","definedIn":"tokens/typography.css"},{"name":"--font-brand","value":"var(--font-sans)","kind":"font","definedIn":"tokens/typography.css"},{"name":"--fw-light","value":"300","kind":"font","definedIn":"tokens/typography.css","annotation":"font"},{"name":"--fw-regular","value":"400","kind":"font","definedIn":"tokens/typography.css","annotation":"font"},{"name":"--fw-medium","value":"500","kind":"font","definedIn":"tokens/typography.css","annotation":"font"},{"name":"--fw-semibold","value":"600","kind":"font","definedIn":"tokens/typography.css","annotation":"font"},{"name":"--fw-bold","value":"700","kind":"font","definedIn":"tokens/typography.css","annotation":"font"},{"name":"--fw-black","value":"800","kind":"font","definedIn":"tokens/typography.css","annotation":"font"},{"name":"--fs-display-xl","value":"72px","kind":"spacing","definedIn":"tokens/typography.css"},{"name":"--fs-display","value":"54px","kind":"spacing","definedIn":"tokens/typography.css"},{"name":"--fs-h1","value":"40px","kind":"spacing","definedIn":"tokens/typography.css"},{"name":"--fs-h2","value":"30px","kind":"spacing","definedIn":"tokens/typography.css"},{"name":"--fs-h3","value":"24px","kind":"spacing","definedIn":"tokens/typography.css"},{"name":"--fs-title","value":"20px","kind":"spacing","definedIn":"tokens/typography.css"},{"name":"--fs-body-lg","value":"18px","kind":"spacing","definedIn":"tokens/typography.css"},{"name":"--fs-body","value":"16px","kind":"spacing","definedIn":"tokens/typography.css"},{"name":"--fs-body-sm","value":"14px","kind":"spacing","definedIn":"tokens/typography.css"},{"name":"--fs-label","value":"13px","kind":"spacing","definedIn":"tokens/typography.css"},{"name":"--fs-caption","value":"12px","kind":"spacing","definedIn":"tokens/typography.css"},{"name":"--fs-micro","value":"11px","kind":"spacing","definedIn":"tokens/typography.css"},{"name":"--lh-tight","value":"1.05","kind":"font","definedIn":"tokens/typography.css","annotation":"font"},{"name":"--lh-snug","value":"1.18","kind":"font","definedIn":"tokens/typography.css","annotation":"font"},{"name":"--lh-display","value":"1.12","kind":"font","definedIn":"tokens/typography.css","annotation":"font"},{"name":"--lh-heading","value":"1.25","kind":"font","definedIn":"tokens/typography.css","annotation":"font"},{"name":"--lh-body","value":"1.62","kind":"font","definedIn":"tokens/typography.css","annotation":"font"},{"name":"--lh-relaxed","value":"1.75","kind":"font","definedIn":"tokens/typography.css","annotation":"font"},{"name":"--ls-tight","value":"-0.01em","kind":"font","definedIn":"tokens/typography.css","annotation":"font"},{"name":"--ls-normal","value":"0","kind":"font","definedIn":"tokens/typography.css","annotation":"font"},{"name":"--ls-wide","value":"0.08em","kind":"font","definedIn":"tokens/typography.css","annotation":"font"},{"name":"--ls-wider","value":"0.16em","kind":"spacing","definedIn":"tokens/typography.css"},{"name":"--ls-widest","value":"0.34em","kind":"spacing","definedIn":"tokens/typography.css"},{"name":"--space-0","value":"0","kind":"spacing","definedIn":"tokens/spacing.css"},{"name":"--space-1","value":"4px","kind":"spacing","definedIn":"tokens/spacing.css"},{"name":"--space-2","value":"8px","kind":"spacing","definedIn":"tokens/spacing.css"},{"name":"--space-3","value":"12px","kind":"spacing","definedIn":"tokens/spacing.css"},{"name":"--space-4","value":"16px","kind":"spacing","definedIn":"tokens/spacing.css"},{"name":"--space-5","value":"20px","kind":"spacing","definedIn":"tokens/spacing.css"},{"name":"--space-6","value":"24px","kind":"spacing","definedIn":"tokens/spacing.css"},{"name":"--space-8","value":"32px","kind":"spacing","definedIn":"tokens/spacing.css"},{"name":"--space-10","value":"40px","kind":"spacing","definedIn":"tokens/spacing.css"},{"name":"--space-12","value":"48px","kind":"spacing","definedIn":"tokens/spacing.css"},{"name":"--space-16","value":"64px","kind":"spacing","definedIn":"tokens/spacing.css"},{"name":"--space-20","value":"80px","kind":"spacing","definedIn":"tokens/spacing.css"},{"name":"--space-24","value":"96px","kind":"spacing","definedIn":"tokens/spacing.css"},{"name":"--space-32","value":"128px","kind":"spacing","definedIn":"tokens/spacing.css"},{"name":"--radius-xs","value":"3px","kind":"radius","definedIn":"tokens/spacing.css"},{"name":"--radius-sm","value":"6px","kind":"radius","definedIn":"tokens/spacing.css"},{"name":"--radius-md","value":"10px","kind":"radius","definedIn":"tokens/spacing.css"},{"name":"--radius-lg","value":"16px","kind":"radius","definedIn":"tokens/spacing.css"},{"name":"--radius-xl","value":"22px","kind":"radius","definedIn":"tokens/spacing.css"},{"name":"--radius-pill","value":"999px","kind":"radius","definedIn":"tokens/spacing.css"},{"name":"--radius-circle","value":"50%","kind":"radius","definedIn":"tokens/spacing.css"},{"name":"--border-hair","value":"1px solid var(--border-subtle)","kind":"color","definedIn":"tokens/spacing.css"},{"name":"--border-ink-1","value":"1.5px solid var(--b3a-ink)","kind":"color","definedIn":"tokens/spacing.css"},{"name":"--border-gold","value":"1px solid var(--b3a-gold)","kind":"color","definedIn":"tokens/spacing.css"},{"name":"--shadow-xs","value":"0 1px 2px rgba(124, 47, 80, 0.06)","kind":"shadow","definedIn":"tokens/spacing.css"},{"name":"--shadow-sm","value":"0 2px 8px -2px rgba(124, 47, 80, 0.10)","kind":"shadow","definedIn":"tokens/spacing.css"},{"name":"--shadow-card","value":"0 14px 38px -18px rgba(124, 47, 80, 0.22)","kind":"shadow","definedIn":"tokens/spacing.css"},{"name":"--shadow-lg","value":"0 28px 60px -24px rgba(58, 30, 44, 0.28)","kind":"shadow","definedIn":"tokens/spacing.css"},{"name":"--shadow-float","value":"0 20px 48px -16px rgba(124, 47, 80, 0.26)","kind":"shadow","definedIn":"tokens/spacing.css"},{"name":"--shadow-inset-line","value":"inset 0 0 0 1px var(--border-subtle)","kind":"shadow","definedIn":"tokens/spacing.css"},{"name":"--ease-out","value":"cubic-bezier(0.22, 0.61, 0.36, 1)","kind":"other","definedIn":"tokens/spacing.css","annotation":"other"},{"name":"--ease-soft","value":"cubic-bezier(0.4, 0.0, 0.2, 1)","kind":"other","definedIn":"tokens/spacing.css","annotation":"other"},{"name":"--dur-fast","value":"140ms","kind":"other","definedIn":"tokens/spacing.css","annotation":"other"},{"name":"--dur-base","value":"240ms","kind":"other","definedIn":"tokens/spacing.css","annotation":"other"},{"name":"--dur-slow","value":"420ms","kind":"other","definedIn":"tokens/spacing.css","annotation":"other"},{"name":"--content-max","value":"1180px","kind":"other","definedIn":"tokens/spacing.css","annotation":"other"},{"name":"--gutter","value":"24px","kind":"spacing","definedIn":"tokens/spacing.css","annotation":"spacing"}],"themes":[],"fonts":[],"brandFonts":[{"family":"Playfair Display","status":"ok","tokens":["--font-serif"],"path":"tokens/typography.css"},{"family":"Jost","status":"ok","tokens":["--font-sans"],"path":"tokens/typography.css"},{"family":"Mulish","status":"ok","tokens":["--font-body"],"path":"tokens/typography.css"}],"source":"spa"}